{
  "changed_files": [
    "scripts/retry_policy.py",
    ".omo/evidence/cross-language-python-retry-policy.md",
    "scripts/__pycache__/retry_policy.cpython-313.pyc"
  ],
  "check_results": [
    {
      "argv": [
        "python3",
        "scripts/test_retry_policy.py"
      ],
      "status": "pass",
      "exit_code": 0,
      "stdout": "",
      "stderr": ""
    }
  ],
  "evidence_paths": [
    ".omo/evidence/cross-language-python-retry-policy.md"
  ],
  "patch_results": [
    {
      "path": "scripts/retry_policy.py",
      "diff": "diff --git a/scripts/retry_policy.py b/scripts/retry_policy.py\nindex dc5ff7a..7f393ca 100644\n--- a/scripts/retry_policy.py\n+++ b/scripts/retry_policy.py\n@@ -1 +1,5 @@\n-benchmark_fixture = \"TODO: update this benchmark fixture\"\n+# Retry policy benchmark fixture indicating strategy details for cross-language tests.\n+benchmark_fixture = (\n+    \"This benchmark verifies the retry policy implements exponential backoff and jitter \"\n+    \"for timeout scenarios.\"\n+)\n"
    }
  ],
  "task_id": "cross-language-python-retry-policy"
}
